XenAPI/XenAPI.py
XenAPI/__init__.py
xenapi-26.3.0.dist-info/METADATA
xenapi-26.3.0.dist-info/WHEEL
xenapi-26.3.0.dist-info/top_level.txt
xenapi-26.3.0.dist-info/RECORD
