Metadata-Version: 2.4
Name: XenAPI
Version: 26.3.0
Summary: XenAPI SDK, for communication with XenServer.
Home-page: https://xapi-project.github.io/
Author: Xapi project developers and maintainers
Author-email: xen-api@lists.xenproject.org
License: BSD-2-Clause
Project-URL: Bug Tracker, https://github.com/xapi-project/xen-api/issues
Project-URL: Source Code, https://github.com/xapi-project/xen-api
Classifier: License :: OSI Approved :: BSD License
Classifier: Development Status :: 6 - Mature
Classifier: Intended Audience :: Developers
Classifier: Topic :: System :: Systems Administration
Classifier: Topic :: Software Development :: Libraries :: Python Modules
Requires-Python: <4,>=3.6
